pdftoAudiobook/__init__.py
pdftoAudiobook/pdftoAudiobook.py
pdfToAudioBookConverter-0.0.2.dist-info/LICENSE.txt
pdfToAudioBookConverter-0.0.2.dist-info/METADATA
pdfToAudioBookConverter-0.0.2.dist-info/WHEEL
pdfToAudioBookConverter-0.0.2.dist-info/top_level.txt
pdfToAudioBookConverter-0.0.2.dist-info/RECORD
