Metadata-Version: 2.1
Name: pdfToAudioBookConverter
Version: 0.0.2
Summary: This package converts a pdf file to audiobooks
Home-page: https://github.com/seigfried1/pdftoaudiobook
Author: Rahul Mishra
Author-email: rahulmishra.psy@gmail.com
License: MIT
Keywords: Audiobooks,pdf,audiobookconverter
Platform: UNKNOWN
Requires-Dist: gTTS (>=2.1.1)
Requires-Dist: PyPDF2 (>=1.26.0)
